{
  "tableContainer": {
    "color": "white",
    "boxShadow": "0px 2px 1px -1px rgba(0,0,0,0.2), 0px 1px 1px 0px rgba(0,0,0,0.14), 0px 1px 3px 0px rgba(0,0,0,0.12)",
    "maxHeight": "calc(100vh - 250px)",
    "borderRadius": "5px"
  },
  "tableHeader": {
    "backgroundColor": "#357376",
    "color": "#fff",
    "cursor": "pointer",
    "userSelect": "none"
  },
  "tableRow": {
    "&:nth-of-type(odd)": {
      "backgroundColor": "#dadada"
    },
    "&:nth-of-type(even)": {
      "backgroundColor": "#ffffff"
    },
    "&:hover": {
      "backgroundColor": "#cacaca"
    }
  },
  "toolBar": {
    "direction": "ltr"
  },
  "spacer": {
    "flex": 0,
    "backgroundColor": "#000"
  },
  "wrapTable": {
    "flexGrow": 1
  }
}
